<?xml version="1.0" encoding="utf-8"?>
<!DOCTYPE hibernate-mapping PUBLIC "-//Hibernate/Hibernate Mapping DTD 3.0//EN"
"http://hibernate.sourceforge.net/hibernate-mapping-3.0.dtd">
<!-- 
    Mapping file autogenerated by MyEclipse Persistence Tools
-->
<hibernate-mapping>
    <class name="com.ithome.pcs.comm.entity.ActExLeavetest" table="ACT_EX_LEAVETEST"  >
        <comment>请假业务测试表</comment>
        <id name="leaveid" type="java.lang.String">
            <column name="LEAVEID" length="32" />
            <generator class="assigned" />
        </id>
        <property name="processid" type="java.lang.String">
            <column name="PROCESSID" length="32">
                <comment>外键（ACT_EX_PROCESS）</comment>
            </column>
        </property>
        <property name="leavename" type="java.lang.String">
            <column name="LEAVENAME" length="1024">
                <comment>请假人姓名</comment>
            </column>
        </property>
        <property name="starttime" type="java.lang.String">
            <column name="STARTTIME" length="128">
                <comment>请假开始时间</comment>
            </column>
        </property>
        <property name="endtime" type="java.lang.String">
            <column name="ENDTIME" length="128">
                <comment>请假结束时间</comment>
            </column>
        </property>
    </class>
</hibernate-mapping>
