<?xml version="1.0" encoding="utf-8"?>
<!DOCTYPE hibernate-mapping PUBLIC "-//Hibernate/Hibernate Mapping DTD 3.0//EN"
"http://hibernate.sourceforge.net/hibernate-mapping-3.0.dtd">
<!-- 
    Mapping file autogenerated by MyEclipse Persistence Tools
-->
<hibernate-mapping>
    <class name="com.ithome.pcs.comm.entity.ActExProcess" table="ACT_EX_PROCESS"  >
        <comment>业务流程表</comment>
        <id name="processid" type="java.lang.String">
            <column name="PROCESSID" length="32" />
            <generator class="assigned" />
        </id>
        <property name="processname" type="java.lang.String">
            <column name="PROCESSNAME" length="128" not-null="true">
                <comment>流程名称</comment>
            </column>
        </property>
        <property name="createusername" type="java.lang.String">
            <column name="CREATEUSERNAME" length="128">
                <comment>创建人</comment>
            </column>
        </property>
        <property name="createuserid" type="java.lang.String">
            <column name="CREATEUSERID" length="32">
                <comment>创建人ID</comment>
            </column>
        </property>
        <property name="createdate" type="java.lang.String">
            <column name="CREATEDATE" length="128">
                <comment>创建时间</comment>
            </column>
        </property>
        <property name="isdeleted" type="java.lang.String">
            <column name="ISDELETED" length="8">
                <comment>流程状态（0：未删除，1：删除）</comment>
            </column>
        </property>
        <property name="procdefkey" type="java.lang.String">
            <column name="PROCDEFKEY" length="128" not-null="true">
                <comment>流程定义KEY</comment>
            </column>
        </property>
        <property name="procdefname" type="java.lang.String">
            <column name="PROCDEFNAME" length="128" not-null="true">
                <comment>流程定义名称</comment>
            </column>
        </property>
        <property name="comments" type="java.lang.String">
            <column name="COMMENTS" length="1024">
                <comment>备注</comment>
            </column>
        </property>
        <property name="urgency" type="java.lang.String">
            <column name="URGENCY" length="8" not-null="true">
                <comment>紧急程度（0：普通，1：中等，2：紧急）</comment>
            </column>
        </property>
    </class>
</hibernate-mapping>
